kicksaw_data_mapping_base/__init__.py
kicksaw_data_mapping_base/cli.py
kicksaw_data_mapping_base/constants/__init__.py
kicksaw_data_mapping_base/constants/columns.py
kicksaw_data_mapping_base/constants/defaults.py
kicksaw_data_mapping_base/constants/scopes.py
kicksaw_data_mapping_base/constants/tokens.py
kicksaw_data_mapping_base/download.py
kicksaw_data_mapping_base/main.py
kicksaw_data_mapping_base-0.1.4.dist-info/entry_points.txt
kicksaw_data_mapping_base-0.1.4.dist-info/WHEEL
kicksaw_data_mapping_base-0.1.4.dist-info/METADATA
kicksaw_data_mapping_base-0.1.4.dist-info/RECORD
